sgk_package/__init__.py
sgk_package-0.0.1.dist-info/LICENSE.txt
sgk_package-0.0.1.dist-info/METADATA
sgk_package-0.0.1.dist-info/WHEEL
sgk_package-0.0.1.dist-info/top_level.txt
sgk_package-0.0.1.dist-info/RECORD
