Metadata-Version: 2.1
Name: sgk-package
Version: 0.0.1
Summary: This is sgk_packages
Home-page: https://github.com/pypa/sampleproject
Author: Swapnali Kapare
Author-email: swapnalikapare02@gmail.com
License: UNKNOWN
Platform: UNKNOWN
Classifier: Programming Language :: Python :: 3
Classifier: License :: OSI Approved :: MIT License
Classifier: Operating System :: OS Independent
Requires-Python: >=3.6
